cometaNLP/DataWrapper.py
cometaNLP/TextAnalyzer.py
cometaNLP/__init__.py
cometanlp-0.0.12.dist-info/METADATA
cometanlp-0.0.12.dist-info/WHEEL
cometanlp-0.0.12.dist-info/licenses/LICENSE
cometanlp-0.0.12.dist-info/RECORD
